Metadata-Version: 1.0
Name: immutable-data-validation
Version: 0.2.1
Summary: Validating basic Python data types.
Home-page: https://github.com/CuriBio/immutable-data-validation
Author: Curi Bio
Author-email: contact@curibio.com
License: MIT
Platform: UNKNOWN
